CHANGES.md
LICENSE.md
MANIFEST.in
README.md
demo.ipynb
setup.cfg
setup.py
cluster_lensing.egg-info/PKG-INFO
cluster_lensing.egg-info/SOURCES.txt
cluster_lensing.egg-info/dependency_links.txt
cluster_lensing.egg-info/top_level.txt
clusterlensing/__init__.py
clusterlensing/clusters.py
clusterlensing/cofm.py
clusterlensing/halobias.py
clusterlensing/nfw.py
clusterlensing/utils.py
clusterlensing/tests/__init__.py
clusterlensing/tests/test_clusters.py
clusterlensing/tests/test_cofm.py
clusterlensing/tests/test_halobias.py
clusterlensing/tests/test_nfw.py