Metadata-Version: 1.1
Name: cluster-lensing
Version: 0.1.0
Summary: Galaxy Cluster and Weak Lensing Tools
Home-page: http://github.com/jesford/cluster-lensing
Author: Jes Ford
Author-email: jesford@uw.edu
License: MIT
Download-URL: http://github.com/jesford/cluster-lensing
Platform: UNKNOWN
Classifier: Intended Audience :: Science/Research
Classifier: License :: OSI Approved :: MIT License
Classifier: Natural Language :: English
Classifier: Programming Language :: Python :: 2.7
